{"_type":"export","__export_format":4,"__export_date":"2024-09-17T01:06:02.090Z","__export_source":"insomnia.desktop.app:v9.3.3","resources":[{"_id":"req_c3df6b7b1ff64d0bb2bd8dc6d2646199","parentId":"wrk_1836e9b08d6e42c5997379f68bb2c6b2","modified":1726534345028,"created":1684965694009,"url":"http://localhost:3333/me","name":"Minha conta","description":"","method":"GET","body":{},"parameters":[],"headers":[],"authentication":{"type":"bearer","token":"eyJhbGciOiJIUzI1NiIsInR5cCI6IkpXVCJ9.eyJuYW1lIjoiU2VuaG9yIFRlc3RlIiwiZW1haWwiOiJ0ZXN0ZUBlbWFpbC5jb20iLCJpYXQiOjE3MjY1MzQwNzMsImV4cCI6MTcyOTEyNjA3Mywic3ViIjoiNjVkNzU5ZDItOGY1My00YjJlLWJkZmItMDYxODQwMmE2NTg5In0.Fik5luVvZMMA5R1poRBHkSzPz3-z8MOusk8YguiXbQE","prefix":"bearer"},"metaSortKey":-1684965694009,"isPrivate":false,"pathParameters":[],"settingStoreCookies":true,"settingSendCookies":true,"settingDisableRenderRequestBody":false,"settingEncodeUrl":true,"settingRebuildPath":true,"settingFollowRedirects":"global","_type":"request"},{"_id":"wrk_1836e9b08d6e42c5997379f68bb2c6b2","parentId":null,"modified":1684965205470,"created":1684965205470,"name":"User","description":"","scope":"collection","_type":"workspace"},{"_id":"req_eb8f626280254b8a8edc886fc51e2e0a","parentId":"wrk_1836e9b08d6e42c5997379f68bb2c6b2","modified":1726534104101,"created":1684965559535,"url":"http://localhost:3333/session","name":"Nova sessão","description":"","method":"POST","body":{"mimeType":"application/json","text":"{\n\t\"email\": \"teste@email.com\",\n\t\"password\": \"123\"\n}"},"parameters":[],"headers":[{"name":"Content-Type","value":"application/json"}],"authentication":{},"metaSortKey":-1684965559535,"isPrivate":false,"settingStoreCookies":true,"settingSendCookies":true,"settingDisableRenderRequestBody":false,"settingEncodeUrl":true,"settingRebuildPath":true,"settingFollowRedirects":"global","_type":"request"},{"_id":"req_3a0122a5b5134fa2bae95591b210bbd1","parentId":"wrk_1836e9b08d6e42c5997379f68bb2c6b2","modified":1726535064658,"created":1684965212241,"url":"http://localhost:3333/users ","name":"Criar usuário","description":"","method":"POST","body":{"mimeType":"multipart/form-data","params":[{"id":"pair_4be332fc750941cfbc603ccad72a255b","name":"name","value":"Senhor Teste","description":"","disabled":false,"type":"text","multiline":false},{"id":"pair_5afa3e83de0046dab7e2dddeecb2d57c","name":"email","value":"teste2@email.com","description":"","disabled":false},{"id":"pair_d6300b70e9d5436e8b5f4a7171ec7ee4","name":"password","value":"123","description":"","disabled":false},{"id":"pair_abc6be2e6aa247c89b9711e1ae4a92e5","name":"file","value":"","description":"","disabled":false,"type":"file","fileName":"/home/micherlane/Imagens/temporada_01_jujutsu_kaisen.jpg"},{"id":"pair_d784af174ef04cffb84e12c6bce6d624","name":"role","value":"ADMIN","description":"","disabled":false}]},"parameters":[],"headers":[{"name":"Content-Type","value":"multipart/form-data"}],"authentication":{},"metaSortKey":-1684965212242,"isPrivate":false,"pathParameters":[],"settingStoreCookies":true,"settingSendCookies":true,"settingDisableRenderRequestBody":false,"settingEncodeUrl":true,"settingRebuildPath":true,"settingFollowRedirects":"global","_type":"request"},{"_id":"req_d55d5e562a524f309f6e293fe2cbf993","parentId":"wrk_1836e9b08d6e42c5997379f68bb2c6b2","modified":1726534330819,"created":1726533955688,"url":"http://localhost:3333/me","name":"Atualizar usuário","description":"","method":"PUT","body":{"mimeType":"multipart/form-data","params":[{"id":"pair_4be332fc750941cfbc603ccad72a255b","name":"name","value":"Senhor Teste","description":"","disabled":false,"type":"text","multiline":false},{"id":"pair_5afa3e83de0046dab7e2dddeecb2d57c","name":"email","value":"teste@email.com","description":"","disabled":false},{"id":"pair_d6300b70e9d5436e8b5f4a7171ec7ee4","name":"password","value":"123","description":"","disabled":false},{"id":"pair_abc6be2e6aa247c89b9711e1ae4a92e5","name":"file","value":"","description":"","disabled":false,"type":"file","fileName":"/home/micherlane/Imagens/processo telhas cerâmica/2_sazoneamento.jpeg"}]},"parameters":[],"headers":[{"name":"Content-Type","value":"multipart/form-data"}],"authentication":{"type":"bearer","token":"eyJhbGciOiJIUzI1NiIsInR5cCI6IkpXVCJ9.eyJuYW1lIjoiU2VuaG9yIFRlc3RlIiwiZW1haWwiOiJ0ZXN0ZUBlbWFpbC5jb20iLCJpYXQiOjE3MjY1MzQwNzMsImV4cCI6MTcyOTEyNjA3Mywic3ViIjoiNjVkNzU5ZDItOGY1My00YjJlLWJkZmItMDYxODQwMmE2NTg5In0.Fik5luVvZMMA5R1poRBHkSzPz3-z8MOusk8YguiXbQE","prefix":"bearer"},"metaSortKey":-1684965212235.75,"isPrivate":false,"pathParameters":[],"settingStoreCookies":true,"settingSendCookies":true,"settingDisableRenderRequestBody":false,"settingEncodeUrl":true,"settingRebuildPath":true,"settingFollowRedirects":"global","_type":"request"},{"_id":"env_a65822fba4588bdd472f29c6cdedc2c809de9d08","parentId":"wrk_1836e9b08d6e42c5997379f68bb2c6b2","modified":1684965205478,"created":1684965205478,"name":"Base Environment","data":{},"dataPropertyOrder":null,"color":null,"isPrivate":false,"metaSortKey":1684965205478,"_type":"environment"},{"_id":"jar_a65822fba4588bdd472f29c6cdedc2c809de9d08","parentId":"wrk_1836e9b08d6e42c5997379f68bb2c6b2","modified":1684965205481,"created":1684965205481,"name":"Default Jar","cookies":[],"_type":"cookie_jar"},{"_id":"spc_6e579ce238264bd5aa8aefb4398fb03b","parentId":"wrk_1836e9b08d6e42c5997379f68bb2c6b2","modified":1684965205472,"created":1684965205472,"fileName":"User","contents":"","contentType":"yaml","_type":"api_spec"}]}